spinsys/__init__.py
spinsys/_test_utils.py
spinsys/py.typed
spinsys/data/__init__.py
spinsys/data/attributes.py
spinsys/data/bit_ops.py
spinsys/data/bit_server.py
spinsys/data/bit_server_http_client.py
spinsys/data/bit_server_http_client_test.py
spinsys/data/bit_server_store.py
spinsys/data/dir_ops.py
spinsys/data/dir_server.py
spinsys/data/dir_server_http_client.py
spinsys/data/dir_server_http_client_test.py
spinsys/data/entries.py
spinsys/data/entry_blocks.py
spinsys/data/entry_levels.py
spinsys/data/entry_types.py
spinsys/data/entry_versions.py
spinsys/data/license_types.py
spinsys/data/licenses.py
spinsys/data/pack_types.py
spinsys/data/path_patterns.py
spinsys/data/permission_grant_types.py
spinsys/data/permission_grants.py
spinsys/data/permissions.py
spinsys/data/sha256.py
spinsys/data/store.py
spinsys/data/client/__init__.py
spinsys/data/client/client.py
spinsys/data/client/client_test.py
spinsys/data/client/file.py
spinsys/data/client/file_test.py
spinsys/data/client/options.py
spinsys/identity/__init__.py
spinsys/identity/aliases.py
spinsys/identity/factor_server.py
spinsys/identity/factor_types.py
spinsys/identity/factorization_types.py
spinsys/identity/factorizations.py
spinsys/identity/factors.py
spinsys/identity/key_server.py
spinsys/identity/key_server_http_client.py
spinsys/identity/key_server_http_client_test.py
spinsys/identity/key_types.py
spinsys/identity/keys.py
spinsys/identity/nonces.py
spinsys/identity/py.typed
spinsys/identity/smoke_test.py
spinsys/spin/__init__.py
spinsys/spin/errors.py
spinsys/spin/names.py
spinsys/spin/paths.py
spinsys/spin/py.typed
spinsys/spin/times.py
spinsys/spin/times_test.py
spinsys/spin/uuids.py
spinsys-0.0.7.dist-info/METADATA
spinsys-0.0.7.dist-info/WHEEL
spinsys-0.0.7.dist-info/licenses/LICENSE
spinsys-0.0.7.dist-info/RECORD
