Metadata-Version: 2.3
Name: spinsys
Version: 0.0.7
Summary: A library for interacting with a Spin system
Project-URL: Homepage, https://github.com/nlandolfi/spinsys
Author-email: "N. C. Landolfi" <crews.fixture.0f@icloud.com>
License-File: LICENSE
Classifier: License :: OSI Approved :: Apache Software License
Classifier: Operating System :: OS Independent
Classifier: Programming Language :: Python :: 3 :: Only
Requires-Python: >=3.8
Requires-Dist: fsspec>=2024.9.0
Requires-Dist: python-dateutil
Requires-Dist: requests>=2.32.3
